{
  "config": "{\"version\":\"5.57\",\"themeCollection\":{\"baseTheme\":{\"name\":\"CY24SU08\",\"version\":\"5.57\",\"type\":2}},\"activeSectionIndex\":1,\"defaultDrillFilterOtherVisuals\":true,\"linguisticSchemaSyncVersion\":2,\"settings\":{\"useNewFilterPaneExperience\":true,\"allowChangeFilterTypes\":true,\"useStylableVisualContainerHeader\":true,\"queryLimitOption\":6,\"exportDataMode\":1,\"useDefaultAggregateDisplayName\":true,\"useEnhancedTooltips\":true},\"objects\":{\"section\":[{\"properties\":{\"verticalAlignment\":{\"expr\":{\"Literal\":{\"Value\":\"'Top'\"}}}}}],\"outspacePane\":[{\"properties\":{\"expanded\":{\"expr\":{\"Literal\":{\"Value\":\"true\"}}}}}]}}",
  "layoutOptimization": 0,
  "pods": [
    {
      "boundSection": "8c98ff7c75385797aa1c",
      "config": "{}",
      "name": "55823b2552d0a33256de"
    }
  ],
  "publicCustomVisuals": [
    "SimpleWaterfall"
  ],
  "resourcePackages": [
    {
      "resourcePackage": {
        "disabled": false,
        "items": [
          {
            "name": "CY24SU08",
            "path": "BaseThemes/CY24SU08.json",
            "type": 202
          }
        ],
        "name": "SharedResources",
        "type": 2
      }
    }
  ],
  "sections": [
    {
      "config": "{}",
      "displayName": "BOP",
      "displayOption": 1,
      "filters": "[]",
      "height": 720.00,
      "name": "8c98ff7c75385797aa1c",
      "visualContainers": [
        {
          "config": "{\"name\":\"3773c9fc0010d20a8e22\",\"layouts\":[{\"id\":0,\"position\":{\"x\":500,\"y\":0,\"width\":480,\"height\":280,\"z\":2000,\"tabOrder\":2000}}],\"singleVisual\":{\"visualType\":\"kpi\",\"projections\":{\"Indicator\":[{\"queryRef\":\"Sum(snowball_output.bop_arr)\"}],\"TrendLine\":[{\"queryRef\":\"snowball_output.customer_key\"}]},\"prototypeQuery\":{\"Version\":2,\"From\":[{\"Name\":\"s\",\"Entity\":\"snowball_output\",\"Type\":0}],\"Select\":[{\"Aggregation\":{\"Expression\":{\"Column\":{\"Expression\":{\"SourceRef\":{\"Source\":\"s\"}},\"Property\":\"bop_arr\"}},\"Function\":0},\"Name\":\"Sum(snowball_output.bop_arr)\",\"NativeReferenceName\":\"Sum of bop_arr\"},{\"Column\":{\"Expression\":{\"SourceRef\":{\"Source\":\"s\"}},\"Property\":\"customer_key\"},\"Name\":\"snowball_output.customer_key\",\"NativeReferenceName\":\"customer_key\"}]},\"drillFilterOtherVisuals\":true,\"vcObjects\":{\"title\":[{\"properties\":{\"text\":{\"expr\":{\"Literal\":{\"Value\":\"'BOP of Particular Customer'\"}}}}}]}}}",
          "filters": "[]",
          "height": 280.00,
          "width": 480.00,
          "x": 500.00,
          "y": 0.00,
          "z": 2000.00
        },
        {
          "config": "{\"name\":\"94f7c3109626ca7624c9\",\"layouts\":[{\"id\":0,\"position\":{\"x\":9.72644376899696,\"y\":289.84802431610944,\"z\":1000,\"width\":480.4863221884499,\"height\":320.9726443768997,\"tabOrder\":1000}}],\"singleVisual\":{\"visualType\":\"slicer\",\"projections\":{\"Values\":[{\"queryRef\":\"snowball_output.customer_key\",\"active\":true}]},\"prototypeQuery\":{\"Version\":2,\"From\":[{\"Name\":\"s\",\"Entity\":\"snowball_output\",\"Type\":0}],\"Select\":[{\"Column\":{\"Expression\":{\"SourceRef\":{\"Source\":\"s\"}},\"Property\":\"customer_key\"},\"Name\":\"snowball_output.customer_key\",\"NativeReferenceName\":\"customer_key\"}]},\"syncGroup\":{\"groupName\":\"customer_key\",\"fieldChanges\":true,\"filterChanges\":true},\"drillFilterOtherVisuals\":true,\"objects\":{\"data\":[{\"properties\":{\"mode\":{\"expr\":{\"Literal\":{\"Value\":\"'Basic'\"}}}}}],\"general\":[{\"properties\":{}}]}}}",
          "filters": "[{\"expression\":{\"Column\":{\"Expression\":{\"SourceRef\":{\"Entity\":\"snowball_output\"}},\"Property\":\"customer_key\"}},\"filter\":{\"Version\":2,\"From\":[{\"Name\":\"subquery\",\"Expression\":{\"Subquery\":{\"Query\":{\"Version\":2,\"From\":[{\"Name\":\"s\",\"Entity\":\"snowball_output\",\"Type\":0}],\"Select\":[{\"Column\":{\"Expression\":{\"SourceRef\":{\"Source\":\"s\"}},\"Property\":\"customer_key\"},\"Name\":\"field\"}],\"OrderBy\":[{\"Direction\":2,\"Expression\":{\"Aggregation\":{\"Expression\":{\"Column\":{\"Expression\":{\"SourceRef\":{\"Source\":\"s\"}},\"Property\":\"customer_key\"}},\"Function\":3}}}],\"Top\":10}}},\"Type\":2},{\"Name\":\"s\",\"Entity\":\"snowball_output\",\"Type\":0}],\"Where\":[{\"Condition\":{\"In\":{\"Expressions\":[{\"Column\":{\"Expression\":{\"SourceRef\":{\"Source\":\"s\"}},\"Property\":\"customer_key\"}}],\"Table\":{\"SourceRef\":{\"Source\":\"subquery\"}}}}}]},\"type\":\"TopN\",\"howCreated\":0,\"isHiddenInViewMode\":false}]",
          "height": 320.97,
          "width": 480.49,
          "x": 9.73,
          "y": 289.85,
          "z": 1000.00
        },
        {
          "config": "{\"name\":\"b60a211138055c191b3b\",\"layouts\":[{\"id\":0,\"position\":{\"x\":9.72644376899696,\"y\":0,\"z\":0,\"width\":479.51367781155017,\"height\":280.1215805471125,\"tabOrder\":0}}],\"singleVisual\":{\"visualType\":\"hundredPercentStackedColumnChart\",\"projections\":{\"Y\":[{\"queryRef\":\"Sum(snowball_output.bop_arr)\"}],\"Category\":[{\"queryRef\":\"snowball_output.customer_key\",\"active\":true}],\"Series\":[{\"queryRef\":\"snowball_output.month_roll.Variation.Date Hierarchy.Year\"}]},\"prototypeQuery\":{\"Version\":2,\"From\":[{\"Name\":\"s\",\"Entity\":\"snowball_output\",\"Type\":0}],\"Select\":[{\"Aggregation\":{\"Expression\":{\"Column\":{\"Expression\":{\"SourceRef\":{\"Source\":\"s\"}},\"Property\":\"bop_arr\"}},\"Function\":0},\"Name\":\"Sum(snowball_output.bop_arr)\",\"NativeReferenceName\":\"Sum of bop_arr\"},{\"Column\":{\"Expression\":{\"SourceRef\":{\"Source\":\"s\"}},\"Property\":\"customer_key\"},\"Name\":\"snowball_output.customer_key\",\"NativeReferenceName\":\"customer_key\"},{\"Column\":{\"Expression\":{\"SourceRef\":{\"Source\":\"s\"}},\"Property\":\"month_roll\"},\"Name\":\"snowball_output.month_roll.Variation.Date Hierarchy.Year\",\"NativeReferenceName\":\"month_roll Year\"}],\"OrderBy\":[{\"Direction\":1,\"Expression\":{\"Column\":{\"Expression\":{\"SourceRef\":{\"Source\":\"s\"}},\"Property\":\"month_roll\"}}}]},\"drillFilterOtherVisuals\":true,\"hasDefaultSort\":true,\"objects\":{\"valueAxis\":[{\"properties\":{\"titleText\":{\"expr\":{\"Literal\":{\"Value\":\"'BOP '\"}}}}}]},\"vcObjects\":{\"title\":[{\"properties\":{\"text\":{\"expr\":{\"Literal\":{\"Value\":\"'Revenue Generated by Customer in BOP'\"}}}}}]}}}",
          "filters": "[{\"expression\":{\"Column\":{\"Expression\":{\"SourceRef\":{\"Entity\":\"snowball_output\"}},\"Property\":\"customer_key\"}},\"filter\":{\"Version\":2,\"From\":[{\"Name\":\"subquery\",\"Expression\":{\"Subquery\":{\"Query\":{\"Version\":2,\"From\":[{\"Name\":\"s\",\"Entity\":\"snowball_output\",\"Type\":0}],\"Select\":[{\"Column\":{\"Expression\":{\"SourceRef\":{\"Source\":\"s\"}},\"Property\":\"customer_key\"},\"Name\":\"field\"}],\"OrderBy\":[{\"Direction\":2,\"Expression\":{\"Aggregation\":{\"Expression\":{\"Column\":{\"Expression\":{\"SourceRef\":{\"Source\":\"s\"}},\"Property\":\"customer_key\"}},\"Function\":3}}}],\"Top\":10}}},\"Type\":2},{\"Name\":\"s\",\"Entity\":\"snowball_output\",\"Type\":0}],\"Where\":[{\"Condition\":{\"In\":{\"Expressions\":[{\"Column\":{\"Expression\":{\"SourceRef\":{\"Source\":\"s\"}},\"Property\":\"customer_key\"}}],\"Table\":{\"SourceRef\":{\"Source\":\"subquery\"}}}}}]},\"type\":\"TopN\",\"howCreated\":0,\"objects\":{\"general\":[{\"properties\":{}}]},\"isHiddenInViewMode\":false}]",
          "height": 280.12,
          "width": 479.51,
          "x": 9.73,
          "y": 0.00,
          "z": 0.00
        }
      ],
      "width": 1280.00
    },
    {
      "config": "{}",
      "displayName": "CRB",
      "displayOption": 1,
      "filters": "[]",
      "height": 720.00,
      "name": "bae09ab820811841e875",
      "ordinal": 1,
      "visualContainers": [
        {
          "config": "{\"name\":\"043a665b3b6a8d342342\",\"layouts\":[{\"id\":0,\"position\":{\"x\":758.6626139817628,\"y\":573.860182370821,\"z\":9000,\"width\":238.29787234042556,\"height\":122.55319148936171,\"tabOrder\":9000}}],\"singleVisual\":{\"visualType\":\"cardVisual\",\"projections\":{\"Data\":[{\"queryRef\":\"Sum(snowball_output.nrr)\"}]},\"prototypeQuery\":{\"Version\":2,\"From\":[{\"Name\":\"s\",\"Entity\":\"snowball_output\",\"Type\":0}],\"Select\":[{\"Aggregation\":{\"Expression\":{\"Column\":{\"Expression\":{\"SourceRef\":{\"Source\":\"s\"}},\"Property\":\"nrr\"}},\"Function\":0},\"Name\":\"Sum(snowball_output.nrr)\",\"NativeReferenceName\":\"Sum of nrr\"}],\"OrderBy\":[{\"Direction\":2,\"Expression\":{\"Aggregation\":{\"Expression\":{\"Column\":{\"Expression\":{\"SourceRef\":{\"Source\":\"s\"}},\"Property\":\"nrr\"}},\"Function\":0}}}]},\"drillFilterOtherVisuals\":true,\"hasDefaultSort\":true,\"objects\":{\"layout\":[{\"properties\":{\"orientation\":{\"expr\":{\"Literal\":{\"Value\":\"2D\"}}},\"style\":{\"expr\":{\"Literal\":{\"Value\":\"'Cards'\"}}}}}],\"label\":[{\"properties\":{\"heading\":{\"expr\":{\"Literal\":{\"Value\":\"'Heading4'\"}}}},\"selector\":{\"id\":\"default\"}}]},\"vcObjects\":{\"title\":[{\"properties\":{\"show\":{\"expr\":{\"Literal\":{\"Value\":\"false\"}}},\"heading\":{\"expr\":{\"Literal\":{\"Value\":\"'Heading3'\"}}},\"fontFamily\":{\"expr\":{\"Literal\":{\"Value\":\"'Calibri'\"}}},\"fontSize\":{\"expr\":{\"Literal\":{\"Value\":\"10D\"}}},\"text\":{\"expr\":{\"Literal\":{\"Value\":\"'hgyj'\"}}},\"alignment\":{\"expr\":{\"Literal\":{\"Value\":\"'center'\"}}}}}],\"subTitle\":[{\"properties\":{\"show\":{\"expr\":{\"Literal\":{\"Value\":\"true\"}}},\"heading\":{\"expr\":{\"Literal\":{\"Value\":\"'Heading4'\"}}},\"titleWrap\":{\"expr\":{\"Literal\":{\"Value\":\"false\"}}}}}],\"general\":[{\"properties\":{\"keepLayerOrder\":{\"expr\":{\"Literal\":{\"Value\":\"false\"}}}}}],\"background\":[{\"properties\":{\"transparency\":{\"expr\":{\"Literal\":{\"Value\":\"14D\"}}}}}]}}}",
          "filters": "[]",
          "height": 122.55,
          "width": 238.30,
          "x": 758.66,
          "y": 573.86,
          "z": 9000.00
        },
        {
          "config": "{\"name\":\"1370444f3d4484c54145\",\"layouts\":[{\"id\":0,\"position\":{\"x\":1021.2765957446807,\"y\":441.580547112462,\"z\":8000,\"width\":238.29787234042556,\"height\":122.55319148936171,\"tabOrder\":8000}}],\"singleVisual\":{\"visualType\":\"cardVisual\",\"projections\":{\"Data\":[{\"queryRef\":\"Sum(snowball_output.grr)\"}]},\"prototypeQuery\":{\"Version\":2,\"From\":[{\"Name\":\"s\",\"Entity\":\"snowball_output\",\"Type\":0}],\"Select\":[{\"Aggregation\":{\"Expression\":{\"Column\":{\"Expression\":{\"SourceRef\":{\"Source\":\"s\"}},\"Property\":\"grr\"}},\"Function\":0},\"Name\":\"Sum(snowball_output.grr)\",\"NativeReferenceName\":\"Sum of grr\"}],\"OrderBy\":[{\"Direction\":2,\"Expression\":{\"Aggregation\":{\"Expression\":{\"Column\":{\"Expression\":{\"SourceRef\":{\"Source\":\"s\"}},\"Property\":\"grr\"}},\"Function\":0}}}]},\"drillFilterOtherVisuals\":true,\"hasDefaultSort\":true,\"objects\":{\"layout\":[{\"properties\":{\"orientation\":{\"expr\":{\"Literal\":{\"Value\":\"2D\"}}},\"maxTiles\":{\"expr\":{\"Literal\":{\"Value\":\"3L\"}}},\"cellPadding\":{\"expr\":{\"Literal\":{\"Value\":\"8L\"}}}}}],\"overFlow\":[{\"properties\":{\"overFlowStyle\":{\"expr\":{\"Literal\":{\"Value\":\"1D\"}}}}}],\"value\":[{\"properties\":{\"fontSize\":{\"expr\":{\"Literal\":{\"Value\":\"45D\"}}}},\"selector\":{\"id\":\"default\"}}]}}}",
          "filters": "[]",
          "height": 122.55,
          "width": 238.30,
          "x": 1021.28,
          "y": 441.58,
          "z": 8000.00
        },
        {
          "config": "{\"name\":\"1dfdeb99219922e28b28\",\"layouts\":[{\"id\":0,\"position\":{\"x\":1021.2765957446807,\"y\":573.860182370821,\"z\":10000,\"width\":238.29787234042556,\"height\":122.55319148936171,\"tabOrder\":10000}}],\"singleVisual\":{\"visualType\":\"cardVisual\",\"projections\":{\"Data\":[{\"queryRef\":\"Sum(snowball_output.eop_arr)\"}]},\"prototypeQuery\":{\"Version\":2,\"From\":[{\"Name\":\"s\",\"Entity\":\"snowball_output\",\"Type\":0}],\"Select\":[{\"Aggregation\":{\"Expression\":{\"Column\":{\"Expression\":{\"SourceRef\":{\"Source\":\"s\"}},\"Property\":\"eop_arr\"}},\"Function\":0},\"Name\":\"Sum(snowball_output.eop_arr)\",\"NativeReferenceName\":\"Sum of eop_arr\"}],\"OrderBy\":[{\"Direction\":2,\"Expression\":{\"Aggregation\":{\"Expression\":{\"Column\":{\"Expression\":{\"SourceRef\":{\"Source\":\"s\"}},\"Property\":\"eop_arr\"}},\"Function\":0}}}]},\"drillFilterOtherVisuals\":true,\"hasDefaultSort\":true,\"objects\":{\"layout\":[{\"properties\":{\"orientation\":{\"expr\":{\"Literal\":{\"Value\":\"2D\"}}},\"style\":{\"expr\":{\"Literal\":{\"Value\":\"'Cards'\"}}}}}],\"label\":[{\"properties\":{\"heading\":{\"expr\":{\"Literal\":{\"Value\":\"'Heading4'\"}}}},\"selector\":{\"id\":\"default\"}}]},\"vcObjects\":{\"title\":[{\"properties\":{\"show\":{\"expr\":{\"Literal\":{\"Value\":\"false\"}}},\"heading\":{\"expr\":{\"Literal\":{\"Value\":\"'Heading3'\"}}},\"fontFamily\":{\"expr\":{\"Literal\":{\"Value\":\"'Calibri'\"}}},\"fontSize\":{\"expr\":{\"Literal\":{\"Value\":\"10D\"}}},\"text\":{\"expr\":{\"Literal\":{\"Value\":\"'hgyj'\"}}},\"alignment\":{\"expr\":{\"Literal\":{\"Value\":\"'center'\"}}}}}],\"subTitle\":[{\"properties\":{\"show\":{\"expr\":{\"Literal\":{\"Value\":\"true\"}}},\"heading\":{\"expr\":{\"Literal\":{\"Value\":\"'Heading4'\"}}},\"titleWrap\":{\"expr\":{\"Literal\":{\"Value\":\"false\"}}}}}],\"general\":[{\"properties\":{\"keepLayerOrder\":{\"expr\":{\"Literal\":{\"Value\":\"false\"}}}}}],\"background\":[{\"properties\":{\"transparency\":{\"expr\":{\"Literal\":{\"Value\":\"14D\"}}}}}]}}}",
          "filters": "[]",
          "height": 122.55,
          "width": 238.30,
          "x": 1021.28,
          "y": 573.86,
          "z": 10000.00
        },
        {
          "config": "{\"name\":\"255b61ee7e6b4b474d84\",\"layouts\":[{\"id\":0,\"position\":{\"x\":0,\"y\":0,\"width\":100,\"height\":40,\"z\":1000,\"tabOrder\":3000}}],\"singleVisual\":{\"visualType\":\"actionButton\",\"drillFilterOtherVisuals\":true,\"objects\":{\"icon\":[{\"properties\":{\"shapeType\":{\"expr\":{\"Literal\":{\"Value\":\"'back'\"}}}},\"selector\":{\"id\":\"default\"}}]},\"vcObjects\":{\"visualLink\":[{\"properties\":{\"show\":{\"expr\":{\"Literal\":{\"Value\":\"true\"}}},\"type\":{\"expr\":{\"Literal\":{\"Value\":\"'Back'\"}}}}}]}},\"howCreated\":\"InsertVisualButton\"}",
          "filters": "[]",
          "height": 40.00,
          "width": 100.00,
          "x": 0.00,
          "y": 0.00,
          "z": 1000.00
        },
        {
          "config": "{\"name\":\"38b55c928405c0a58976\",\"layouts\":[{\"id\":0,\"position\":{\"x\":9.72644376899696,\"y\":39.87841945288754,\"z\":0,\"width\":1270.273556231003,\"height\":358.90577507598783,\"tabOrder\":0}}],\"singleVisual\":{\"visualType\":\"SimpleWaterfall\",\"projections\":{\"measure\":[{\"queryRef\":\"Sum(snowball_output.bop_arr)\"},{\"queryRef\":\"Sum(snowball_output.product_churn)\"},{\"queryRef\":\"Sum(snowball_output.customer_churn)\"},{\"queryRef\":\"Sum(snowball_output.downsell)\"},{\"queryRef\":\"Sum(snowball_output.grr)\"},{\"queryRef\":\"Sum(snowball_output.cross_sell)\"},{\"queryRef\":\"Sum(snowball_output.upsell)\"},{\"queryRef\":\"Sum(snowball_output.nrr)\"},{\"queryRef\":\"Sum(snowball_output.new_customer)\"},{\"queryRef\":\"Sum(snowball_output.eop_arr)\"}]},\"prototypeQuery\":{\"Version\":2,\"From\":[{\"Name\":\"s\",\"Entity\":\"snowball_output\",\"Type\":0}],\"Select\":[{\"Aggregation\":{\"Expression\":{\"Column\":{\"Expression\":{\"SourceRef\":{\"Source\":\"s\"}},\"Property\":\"bop_arr\"}},\"Function\":0},\"Name\":\"Sum(snowball_output.bop_arr)\",\"NativeReferenceName\":\"Sum of bop_arr\"},{\"Aggregation\":{\"Expression\":{\"Column\":{\"Expression\":{\"SourceRef\":{\"Source\":\"s\"}},\"Property\":\"customer_churn\"}},\"Function\":0},\"Name\":\"Sum(snowball_output.customer_churn)\",\"NativeReferenceName\":\"Sum of customer_churn\"},{\"Aggregation\":{\"Expression\":{\"Column\":{\"Expression\":{\"SourceRef\":{\"Source\":\"s\"}},\"Property\":\"downsell\"}},\"Function\":0},\"Name\":\"Sum(snowball_output.downsell)\",\"NativeReferenceName\":\"Sum of downsell\"},{\"Aggregation\":{\"Expression\":{\"Column\":{\"Expression\":{\"SourceRef\":{\"Source\":\"s\"}},\"Property\":\"grr\"}},\"Function\":0},\"Name\":\"Sum(snowball_output.grr)\",\"NativeReferenceName\":\"Sum of grr\"},{\"Aggregation\":{\"Expression\":{\"Column\":{\"Expression\":{\"SourceRef\":{\"Source\":\"s\"}},\"Property\":\"new_customer\"}},\"Function\":0},\"Name\":\"Sum(snowball_output.new_customer)\",\"NativeReferenceName\":\"Sum of new_customer\"},{\"Aggregation\":{\"Expression\":{\"Column\":{\"Expression\":{\"SourceRef\":{\"Source\":\"s\"}},\"Property\":\"nrr\"}},\"Function\":0},\"Name\":\"Sum(snowball_output.nrr)\",\"NativeReferenceName\":\"Sum of nrr\"},{\"Aggregation\":{\"Expression\":{\"Column\":{\"Expression\":{\"SourceRef\":{\"Source\":\"s\"}},\"Property\":\"product_churn\"}},\"Function\":0},\"Name\":\"Sum(snowball_output.product_churn)\",\"NativeReferenceName\":\"Sum of product_churn\"},{\"Aggregation\":{\"Expression\":{\"Column\":{\"Expression\":{\"SourceRef\":{\"Source\":\"s\"}},\"Property\":\"cross_sell\"}},\"Function\":0},\"Name\":\"Sum(snowball_output.cross_sell)\",\"NativeReferenceName\":\"Sum of cross_sell\"},{\"Aggregation\":{\"Expression\":{\"Column\":{\"Expression\":{\"SourceRef\":{\"Source\":\"s\"}},\"Property\":\"eop_arr\"}},\"Function\":0},\"Name\":\"Sum(snowball_output.eop_arr)\",\"NativeReferenceName\":\"Sum of eop_arr\"},{\"Aggregation\":{\"Expression\":{\"Column\":{\"Expression\":{\"SourceRef\":{\"Source\":\"s\"}},\"Property\":\"upsell\"}},\"Function\":0},\"Name\":\"Sum(snowball_output.upsell)\",\"NativeReferenceName\":\"Sum of upsell\"}],\"OrderBy\":[{\"Direction\":2,\"Expression\":{\"Aggregation\":{\"Expression\":{\"Column\":{\"Expression\":{\"SourceRef\":{\"Source\":\"s\"}},\"Property\":\"bop_arr\"}},\"Function\":0}}}]},\"drillFilterOtherVisuals\":true,\"hasDefaultSort\":true,\"objects\":{\"definePillars\":[{\"properties\":{\"pillars\":{\"expr\":{\"Literal\":{\"Value\":\"true\"}}}},\"selector\":{\"metadata\":\"Sum(snowball_output.bop_arr)\"}},{\"properties\":{\"pillars\":{\"expr\":{\"Literal\":{\"Value\":\"true\"}}}},\"selector\":{\"metadata\":\"Sum(snowball_output.grr)\"}},{\"properties\":{\"pillars\":{\"expr\":{\"Literal\":{\"Value\":\"true\"}}}},\"selector\":{\"metadata\":\"Sum(snowball_output.nrr)\"}},{\"properties\":{\"pillars\":{\"expr\":{\"Literal\":{\"Value\":\"true\"}}}},\"selector\":{\"metadata\":\"Sum(snowball_output.eop_arr)\"}}],\"sentimentColor\":[{\"properties\":{\"sentimentColorTotal\":{\"solid\":{\"color\":{\"expr\":{\"Literal\":{\"Value\":\"'#1B119E'\"}}}}}}}]},\"vcObjects\":{\"title\":[{\"properties\":{\"text\":{\"expr\":{\"Literal\":{\"Value\":\"''\"}}}}}]}}}",
          "filters": "[{\"name\":\"edc70224a5380dd304ba\",\"filter\":{\"Version\":2,\"From\":[{\"Name\":\"s\",\"Entity\":\"snowball_output\",\"Type\":0}],\"Where\":[{\"Condition\":{\"Not\":{\"Expression\":{\"In\":{\"Expressions\":[{\"Column\":{\"Expression\":{\"SourceRef\":{\"Source\":\"s\"}},\"Property\":\"period_type\"}}],\"Values\":[[{\"Literal\":{\"Value\":\"'ltm'\"}}]]}}}}}]},\"type\":\"Exclude\",\"howCreated\":4,\"filterExpressionMetadata\":{\"expressions\":[{\"Column\":{\"Expression\":{\"SourceRef\":{\"Entity\":\"snowball_output\"}},\"Property\":\"period_type\"}}],\"cachedValueItems\":[{\"identities\":[{\"scopeId\":{\"Comparison\":{\"ComparisonKind\":0,\"Left\":{\"Column\":{\"Expression\":{\"SourceRef\":{\"Entity\":\"snowball_output\"}},\"Property\":\"period_type\"}},\"Right\":{\"Literal\":{\"Value\":\"'ltm'\"}}}}}],\"valueMap\":{\"0\":\"ltm\"}}]}}]",
          "height": 358.91,
          "width": 1270.27,
          "x": 9.73,
          "y": 39.88,
          "z": 0.00
        },
        {
          "config": "{\"name\":\"40d2dc599618a4079da4\",\"layouts\":[{\"id\":0,\"position\":{\"x\":502.8571428571429,\"y\":575.8054711246201,\"z\":5000,\"width\":243.16109422492403,\"height\":69.05775075987842,\"tabOrder\":5000}}],\"singleVisual\":{\"visualType\":\"slicer\",\"projections\":{\"Values\":[{\"queryRef\":\"snowball_output.month_roll.Variation.Date Hierarchy.Quarter1\",\"active\":true}]},\"prototypeQuery\":{\"Version\":2,\"From\":[{\"Name\":\"s\",\"Entity\":\"snowball_output\",\"Type\":0}],\"Select\":[{\"HierarchyLevel\":{\"Expression\":{\"Hierarchy\":{\"Expression\":{\"PropertyVariationSource\":{\"Expression\":{\"SourceRef\":{\"Source\":\"s\"}},\"Name\":\"Variation\",\"Property\":\"month_roll\"}},\"Hierarchy\":\"Date Hierarchy\"}},\"Level\":\"Quarter\"},\"Name\":\"snowball_output.month_roll.Variation.Date Hierarchy.Quarter1\",\"NativeReferenceName\":\"month_roll Quarter1\"}]},\"drillFilterOtherVisuals\":true,\"objects\":{\"data\":[{\"properties\":{\"mode\":{\"expr\":{\"Literal\":{\"Value\":\"'Dropdown'\"}}}}}],\"header\":[{\"properties\":{\"text\":{\"expr\":{\"Literal\":{\"Value\":\"'Quater'\"}}}}}],\"general\":[{\"properties\":{}}]}}}",
          "filters": "[]",
          "height": 69.06,
          "width": 243.16,
          "x": 502.86,
          "y": 575.81,
          "z": 5000.00
        },
        {
          "config": "{\"name\":\"5059352014ae89228578\",\"layouts\":[{\"id\":0,\"position\":{\"x\":502.8571428571429,\"y\":644.8632218844986,\"z\":6000,\"width\":243.16109422492403,\"height\":63.22188449848024,\"tabOrder\":6000}}],\"singleVisual\":{\"visualType\":\"slicer\",\"projections\":{\"Values\":[{\"queryRef\":\"snowball_output.period_type\",\"active\":true}]},\"prototypeQuery\":{\"Version\":2,\"From\":[{\"Name\":\"s\",\"Entity\":\"snowball_output\",\"Type\":0}],\"Select\":[{\"Column\":{\"Expression\":{\"SourceRef\":{\"Source\":\"s\"}},\"Property\":\"period_type\"},\"Name\":\"snowball_output.period_type\",\"NativeReferenceName\":\"period_type\"}]},\"drillFilterOtherVisuals\":true,\"objects\":{\"data\":[{\"properties\":{\"mode\":{\"expr\":{\"Literal\":{\"Value\":\"'Dropdown'\"}}}}}],\"general\":[{\"properties\":{\"filter\":{\"filter\":{\"Version\":2,\"From\":[{\"Name\":\"s\",\"Entity\":\"snowball_output\",\"Type\":0}],\"Where\":[{\"Condition\":{\"In\":{\"Expressions\":[{\"Column\":{\"Expression\":{\"SourceRef\":{\"Source\":\"s\"}},\"Property\":\"period_type\"}}],\"Values\":[[{\"Literal\":{\"Value\":\"'lm'\"}}]]}}}]}}}}]}}}",
          "filters": "[]",
          "height": 63.22,
          "width": 243.16,
          "x": 502.86,
          "y": 644.86,
          "z": 6000.00
        },
        {
          "config": "{\"name\":\"69abf53ee046a084e83d\",\"layouts\":[{\"id\":0,\"position\":{\"x\":9.72644376899696,\"y\":398.7841945288754,\"z\":2000,\"width\":480.4863221884499,\"height\":320.9726443768997,\"tabOrder\":1000}}],\"singleVisual\":{\"visualType\":\"slicer\",\"projections\":{\"Values\":[{\"queryRef\":\"snowball_output.customer_key\",\"active\":true}]},\"prototypeQuery\":{\"Version\":2,\"From\":[{\"Name\":\"s\",\"Entity\":\"snowball_output\",\"Type\":0}],\"Select\":[{\"Column\":{\"Expression\":{\"SourceRef\":{\"Source\":\"s\"}},\"Property\":\"customer_key\"},\"Name\":\"snowball_output.customer_key\",\"NativeReferenceName\":\"customer_key\"}]},\"syncGroup\":{\"groupName\":\"customer_key\",\"fieldChanges\":true,\"filterChanges\":true},\"drillFilterOtherVisuals\":true,\"objects\":{\"data\":[{\"properties\":{\"mode\":{\"expr\":{\"Literal\":{\"Value\":\"'Basic'\"}}}}}],\"general\":[{\"properties\":{}}]}}}",
          "filters": "[{\"expression\":{\"Column\":{\"Expression\":{\"SourceRef\":{\"Entity\":\"snowball_output\"}},\"Property\":\"customer_key\"}},\"filter\":{\"Version\":2,\"From\":[{\"Name\":\"subquery\",\"Expression\":{\"Subquery\":{\"Query\":{\"Version\":2,\"From\":[{\"Name\":\"s\",\"Entity\":\"snowball_output\",\"Type\":0}],\"Select\":[{\"Column\":{\"Expression\":{\"SourceRef\":{\"Source\":\"s\"}},\"Property\":\"customer_key\"},\"Name\":\"field\"}],\"OrderBy\":[{\"Direction\":2,\"Expression\":{\"Aggregation\":{\"Expression\":{\"Column\":{\"Expression\":{\"SourceRef\":{\"Source\":\"s\"}},\"Property\":\"customer_key\"}},\"Function\":3}}}],\"Top\":10}}},\"Type\":2},{\"Name\":\"s\",\"Entity\":\"snowball_output\",\"Type\":0}],\"Where\":[{\"Condition\":{\"In\":{\"Expressions\":[{\"Column\":{\"Expression\":{\"SourceRef\":{\"Source\":\"s\"}},\"Property\":\"customer_key\"}}],\"Table\":{\"SourceRef\":{\"Source\":\"subquery\"}}}}}]},\"type\":\"TopN\",\"howCreated\":0,\"isHiddenInViewMode\":false}]",
          "height": 320.97,
          "width": 480.49,
          "x": 9.73,
          "y": 398.78,
          "z": 2000.00
        },
        {
          "config": "{\"name\":\"c9b921e5a2deaece8be0\",\"layouts\":[{\"id\":0,\"position\":{\"x\":502.8571428571429,\"y\":506.74772036474167,\"z\":4000,\"width\":243.16109422492403,\"height\":69.05775075987842,\"tabOrder\":4000}}],\"singleVisual\":{\"visualType\":\"slicer\",\"projections\":{\"Values\":[{\"queryRef\":\"snowball_output.month_roll.Variation.Date Hierarchy.Month1\",\"active\":true}]},\"prototypeQuery\":{\"Version\":2,\"From\":[{\"Name\":\"s\",\"Entity\":\"snowball_output\",\"Type\":0}],\"Select\":[{\"HierarchyLevel\":{\"Expression\":{\"Hierarchy\":{\"Expression\":{\"PropertyVariationSource\":{\"Expression\":{\"SourceRef\":{\"Source\":\"s\"}},\"Name\":\"Variation\",\"Property\":\"month_roll\"}},\"Hierarchy\":\"Date Hierarchy\"}},\"Level\":\"Month\"},\"Name\":\"snowball_output.month_roll.Variation.Date Hierarchy.Month1\",\"NativeReferenceName\":\"month_roll Month1\"}]},\"drillFilterOtherVisuals\":true,\"objects\":{\"data\":[{\"properties\":{\"mode\":{\"expr\":{\"Literal\":{\"Value\":\"'Dropdown'\"}}}}}],\"header\":[{\"properties\":{\"text\":{\"expr\":{\"Literal\":{\"Value\":\"'Month'\"}}}}}],\"general\":[{\"properties\":{}}]}}}",
          "filters": "[]",
          "height": 69.06,
          "width": 243.16,
          "x": 502.86,
          "y": 506.75,
          "z": 4000.00
        },
        {
          "config": "{\"name\":\"ec9f3d9e553a83d940a3\",\"layouts\":[{\"id\":0,\"position\":{\"x\":758.6626139817628,\"y\":441.580547112462,\"z\":7000,\"width\":238.29787234042556,\"height\":122.55319148936171,\"tabOrder\":7000}}],\"singleVisual\":{\"visualType\":\"cardVisual\",\"projections\":{\"Data\":[{\"queryRef\":\"snowball_output.total_bop\"}]},\"prototypeQuery\":{\"Version\":2,\"From\":[{\"Name\":\"s\",\"Entity\":\"snowball_output\",\"Type\":0}],\"Select\":[{\"Measure\":{\"Expression\":{\"SourceRef\":{\"Source\":\"s\"}},\"Property\":\"total_bop\"},\"Name\":\"snowball_output.total_bop\",\"NativeReferenceName\":\"total_bop\"}],\"OrderBy\":[{\"Direction\":2,\"Expression\":{\"Measure\":{\"Expression\":{\"SourceRef\":{\"Source\":\"s\"}},\"Property\":\"total_bop\"}}}]},\"drillFilterOtherVisuals\":true,\"hasDefaultSort\":true,\"objects\":{\"layout\":[{\"properties\":{\"orientation\":{\"expr\":{\"Literal\":{\"Value\":\"2D\"}}},\"style\":{\"expr\":{\"Literal\":{\"Value\":\"'Cards'\"}}}}}],\"label\":[{\"properties\":{\"heading\":{\"expr\":{\"Literal\":{\"Value\":\"'Heading4'\"}}}},\"selector\":{\"id\":\"default\"}}]},\"vcObjects\":{\"title\":[{\"properties\":{\"show\":{\"expr\":{\"Literal\":{\"Value\":\"false\"}}},\"heading\":{\"expr\":{\"Literal\":{\"Value\":\"'Heading3'\"}}},\"fontFamily\":{\"expr\":{\"Literal\":{\"Value\":\"'Calibri'\"}}},\"fontSize\":{\"expr\":{\"Literal\":{\"Value\":\"10D\"}}},\"text\":{\"expr\":{\"Literal\":{\"Value\":\"'hgyj'\"}}},\"alignment\":{\"expr\":{\"Literal\":{\"Value\":\"'center'\"}}}}}],\"subTitle\":[{\"properties\":{\"show\":{\"expr\":{\"Literal\":{\"Value\":\"true\"}}},\"heading\":{\"expr\":{\"Literal\":{\"Value\":\"'Heading4'\"}}},\"titleWrap\":{\"expr\":{\"Literal\":{\"Value\":\"false\"}}}}}],\"general\":[{\"properties\":{\"keepLayerOrder\":{\"expr\":{\"Literal\":{\"Value\":\"false\"}}}}}],\"background\":[{\"properties\":{\"transparency\":{\"expr\":{\"Literal\":{\"Value\":\"14D\"}}}}}]}}}",
          "filters": "[]",
          "height": 122.55,
          "width": 238.30,
          "x": 758.66,
          "y": 441.58,
          "z": 7000.00
        },
        {
          "config": "{\"name\":\"fc19e139b00c4669004d\",\"layouts\":[{\"id\":0,\"position\":{\"x\":502.8571428571429,\"y\":431.85410334346506,\"z\":3000,\"width\":243.16109422492403,\"height\":69.05775075987842,\"tabOrder\":2000}}],\"singleVisual\":{\"visualType\":\"slicer\",\"projections\":{\"Values\":[{\"queryRef\":\"snowball_output.month_roll.Variation.Date Hierarchy.Year1\",\"active\":true}]},\"prototypeQuery\":{\"Version\":2,\"From\":[{\"Name\":\"s\",\"Entity\":\"snowball_output\",\"Type\":0}],\"Select\":[{\"HierarchyLevel\":{\"Expression\":{\"Hierarchy\":{\"Expression\":{\"PropertyVariationSource\":{\"Expression\":{\"SourceRef\":{\"Source\":\"s\"}},\"Name\":\"Variation\",\"Property\":\"month_roll\"}},\"Hierarchy\":\"Date Hierarchy\"}},\"Level\":\"Year\"},\"Name\":\"snowball_output.month_roll.Variation.Date Hierarchy.Year1\",\"NativeReferenceName\":\"month_roll Year1\"}],\"OrderBy\":[{\"Direction\":1,\"Expression\":{\"HierarchyLevel\":{\"Expression\":{\"Hierarchy\":{\"Expression\":{\"PropertyVariationSource\":{\"Expression\":{\"SourceRef\":{\"Source\":\"s\"}},\"Name\":\"Variation\",\"Property\":\"month_roll\"}},\"Hierarchy\":\"Date Hierarchy\"}},\"Level\":\"Year\"}}}]},\"expansionStates\":[{\"roles\":[\"Values\"],\"levels\":[{\"queryRefs\":[\"snowball_output.month_roll.Variation.Date Hierarchy.Year1\"],\"isCollapsed\":true,\"isPinned\":true}],\"root\":{\"identityValues\":null}}],\"drillFilterOtherVisuals\":true,\"hasDefaultSort\":true,\"objects\":{\"data\":[{\"properties\":{\"mode\":{\"expr\":{\"Literal\":{\"Value\":\"'Dropdown'\"}}}}}],\"general\":[{\"properties\":{}}]}}}",
          "filters": "[]",
          "height": 69.06,
          "width": 243.16,
          "x": 502.86,
          "y": 431.85,
          "z": 3000.00
        }
      ],
      "width": 1280.00
    }
  ]
}